{"note":"This file is an internal implementation detail to speed up HTML report generation. Its format can change at any time. You might be looking for the JSON report: https://coverage.rtfd.io/cmd.html#cmd-json","format":5,"version":"7.5.3","globals":"de2b9c8aec8b989ed20e90864c7829b3","files":{"main_py":{"hash":"691a1dea535cc8865b2af2c9b5262ece","index":{"url":"main_py.html","file":"main.py","description":"","nums":{"precision":0,"n_files":1,"n_statements":14,"n_excluded":3,"n_missing":0,"n_branches":0,"n_partial_branches":0,"n_missing_branches":0}}},"z_e799482a96fa5115_example_py":{"hash":"08e8fa9ab87c6c0899f9771a73700b6d","index":{"url":"z_e799482a96fa5115_example_py.html","file":"pyskel/example.py","description":"","nums":{"precision":0,"n_files":1,"n_statements":2,"n_excluded":0,"n_missing":0,"n_branches":0,"n_partial_branches":0,"n_missing_branches":0}}},"z_e799482a96fa5115_run_py":{"hash":"c146ce5a6ca6836435d7f4e20dcf1175","index":{"url":"z_e799482a96fa5115_run_py.html","file":"pyskel/run.py","description":"","nums":{"precision":0,"n_files":1,"n_statements":10,"n_excluded":0,"n_missing":0,"n_branches":0,"n_partial_branches":0,"n_missing_branches":0}}},"z_e799482a96fa5115_utilities_py":{"hash":"5fe6f011e247636879a31291204692f6","index":{"url":"z_e799482a96fa5115_utilities_py.html","file":"pyskel/utilities.py","description":"","nums":{"precision":0,"n_files":1,"n_statements":20,"n_excluded":0,"n_missing":2,"n_branches":0,"n_partial_branches":0,"n_missing_branches":0}}},"z_6a07bf5284442d43_logger_py":{"hash":"f9f77a13f95b127bfad3d05f694b4805","index":{"url":"z_6a07bf5284442d43_logger_py.html","file":"utilities/log/logger.py","description":"","nums":{"precision":0,"n_files":1,"n_statements":39,"n_excluded":0,"n_missing":0,"n_branches":0,"n_partial_branches":0,"n_missing_branches":0}}}}}